docconvert/__init__.py
docconvert/cli.py
docconvert/configuration.py
docconvert/core.py
docconvert/dict_utils.py
docconvert/line_utils.py
docconvert/parser/__init__.py
docconvert/parser/base.py
docconvert/parser/docstring.py
docconvert/parser/epytext.py
docconvert/parser/module.py
docconvert/parser/rest.py
docconvert/writer/__init__.py
docconvert/writer/base.py
docconvert/writer/epytext.py
docconvert/writer/google.py
docconvert/writer/numpy.py
docconvert/writer/rest.py
docconvert-2.2.0.dist-info/LICENSE.md
docconvert-2.2.0.dist-info/METADATA
docconvert-2.2.0.dist-info/WHEEL
docconvert-2.2.0.dist-info/entry_points.txt
docconvert-2.2.0.dist-info/top_level.txt
docconvert-2.2.0.dist-info/RECORD
