Metadata-Version: 2.1
Name: docconvert
Version: 2.2.0
Summary: Convert and conform package docstrings to a new style
Home-page: https://github.com/cbillingham/docconvert
License: BSD 3-Clause License
Project-URL: Documentation, https://docconvert.readthedocs.io/
Project-URL: Changelog, https://docconvert.readthedocs.io/en/stable/release_notes.html
Project-URL: Issue Tracker, https://github.com/cbillingham/docconvert/issues
Keywords: docstrings,convert-docstrings,formatter
Classifier: Development Status :: 5 - Production/Stable
Classifier: Intended Audience :: Developers
Classifier: License :: OSI Approved :: BSD License
Classifier: Natural Language :: English
Classifier: Operating System :: OS Independent
Classifier: Programming Language :: Python :: 3
Classifier: Programming Language :: Python :: 3.9
Classifier: Programming Language :: Python :: 3.10
Classifier: Programming Language :: Python :: 3.11
Classifier: Programming Language :: Python :: 3.12
Classifier: Programming Language :: Python :: 3.13
Requires-Python: >=3.6
License-File: LICENSE.md
Requires-Dist: six
Requires-Dist: enum34 ; python_version < "3.4"
Provides-Extra: dev
Requires-Dist: black ; extra == 'dev'
Requires-Dist: tox ; extra == 'dev'
Requires-Dist: pre-commit ; extra == 'dev'
Provides-Extra: doc
Requires-Dist: sphinx ; extra == 'doc'
Requires-Dist: sphinx-rtd-theme ; extra == 'doc'
